dataquery/__init__.py
dataquery/auth.py
dataquery/auto_download.py
dataquery/cli.py
dataquery/client.py
dataquery/config.py
dataquery/connection_pool.py
dataquery/dataquery.py
dataquery/exceptions.py
dataquery/logging_config.py
dataquery/models.py
dataquery/py.typed
dataquery/rate_limiter.py
dataquery/retry.py
dataquery/utils.py
dataquery_sdk-0.0.7.dist-info/licenses/LICENSE
dataquery_sdk-0.0.7.dist-info/METADATA
dataquery_sdk-0.0.7.dist-info/WHEEL
dataquery_sdk-0.0.7.dist-info/entry_points.txt
dataquery_sdk-0.0.7.dist-info/top_level.txt
dataquery_sdk-0.0.7.dist-info/RECORD
