Metadata-Version: 2.4
Name: dataquery-sdk
Version: 0.0.7
Summary: Python SDK for DATAQUERY Data API - Query, download, and check availability of economic data files
Author-email: DATAQUERY SDK Team <support@dataquery.com>
Project-URL: Homepage, https://github.com/dataquery/dataquery-sdk
Project-URL: Bug Tracker, https://github.com/dataquery/dataquery-sdk/issues
Project-URL: Documentation, https://github.com/dataquery/dataquery-sdk/wiki
Project-URL: Source Code, https://github.com/dataquery/dataquery-sdk
Keywords: dataquery,data,api,economic,financial,download,async,oauth,rate-limiting,sdk
Classifier: Development Status :: 5 - Production/Stable
Classifier: Intended Audience :: Developers
Classifier: Intended Audience :: Financial and Insurance Industry
Classifier: Intended Audience :: Science/Research
Classifier: License :: OSI Approved :: MIT License
Classifier: Operating System :: OS Independent
Classifier: Programming Language :: Python :: 3
Classifier: Programming Language :: Python :: 3.10
Classifier: Programming Language :: Python :: 3.11
Classifier: Programming Language :: Python :: 3.12
Classifier: Programming Language :: Python :: 3.13
Classifier: Topic :: Software Development :: Libraries :: Python Modules
Classifier: Topic :: Office/Business :: Financial
Classifier: Topic :: Scientific/Engineering :: Information Analysis
Classifier: Topic :: Internet :: WWW/HTTP :: Dynamic Content
Requires-Python: >=3.10
License-File: LICENSE
Requires-Dist: aiohttp<4.0.0,>=3.8.0
Requires-Dist: pydantic<3.0.0,>=2.0.0
Requires-Dist: structlog>=23.0.0
Requires-Dist: python-dotenv>=1.0.0
Provides-Extra: dev
Requires-Dist: pytest>=7.0.0; extra == "dev"
Requires-Dist: pytest-asyncio>=0.21.0; extra == "dev"
Requires-Dist: pytest-cov>=4.0.0; extra == "dev"
Requires-Dist: black>=23.0.0; extra == "dev"
Requires-Dist: flake8>=6.0.0; extra == "dev"
Requires-Dist: mypy>=1.5.0; extra == "dev"
Requires-Dist: isort>=5.12.0; extra == "dev"
Requires-Dist: pre-commit>=3.0.0; extra == "dev"
Requires-Dist: pip-audit>=2.7.0; extra == "dev"
Requires-Dist: build>=1.3.0; extra == "dev"
Requires-Dist: twine>=4.0.0; extra == "dev"
Provides-Extra: docs
Requires-Dist: mkdocs>=1.5.0; extra == "docs"
Requires-Dist: mkdocs-material>=9.0.0; extra == "docs"
Requires-Dist: mkdocstrings[python]>=0.24.0; extra == "docs"
Requires-Dist: mike>=1.1.0; extra == "docs"
Provides-Extra: pandas
Requires-Dist: pandas>=2.0.0; extra == "pandas"
Provides-Extra: all
Requires-Dist: pytest>=7.0.0; extra == "all"
Requires-Dist: pytest-asyncio>=0.21.0; extra == "all"
Requires-Dist: pytest-cov>=4.0.0; extra == "all"
Requires-Dist: black>=23.0.0; extra == "all"
Requires-Dist: flake8>=6.0.0; extra == "all"
Requires-Dist: mypy>=1.5.0; extra == "all"
Requires-Dist: isort>=5.12.0; extra == "all"
Requires-Dist: pre-commit>=3.0.0; extra == "all"
Requires-Dist: mkdocs>=1.5.0; extra == "all"
Requires-Dist: mkdocs-material>=9.0.0; extra == "all"
Requires-Dist: mkdocstrings[python]>=0.24.0; extra == "all"
Requires-Dist: mike>=1.1.0; extra == "all"
Requires-Dist: pandas>=2.0.0; extra == "all"
Requires-Dist: pip-audit>=2.7.0; extra == "all"
Requires-Dist: build>=1.3.0; extra == "all"
Dynamic: license-file
